{
    "Version": 1.011,
    "ReferenceType": "Issues",
    "GridColumns": [
        "IssueId",
        "TitleBody",
        "Comments",
        "StartTime",
        "CompletionTime",
        "Status",
        "Manager",
        "Owner",
        "ClassA",
        "Updator",
        "UpdatedTime"
    ],
    "EditorColumns": [
        "Comments",
        "IssueId",
        "Ver",
        "Title",
        "Body",
        "StartTime",
        "CompletionTime",
        "Status",
        "Manager",
        "Owner",
        "ClassA"
    ],
    "LinkColumns": [
        "IssueId",
        "Title",
        "StartTime",
        "CompletionTime",
        "Status",
        "Owner",
        "Updator",
        "UpdatedTime",
        "ClassA"
    ],
    "HistoryColumns": [
        "Ver",
        "Title",
        "Comments",
        "StartTime",
        "CompletionTime",
        "Status",
        "Owner",
        "Updator",
        "UpdatedTime"
    ],
    "Columns": [
        {
            "ColumnName": "AttachmentsA",
            "LabelText": "Attached_files"
        },
        {
            "ColumnName": "ClassA",
            "LabelText": "Issue_category",
            "ChoicesText": "Incident_category1\nIncident_category2\nIncident_category3\nIncident_category4\nIncident_category5"
        },
        {
            "ColumnName": "Status",
            "ChoicesText": "100,Not_start,Not,status-new\n150,Preparation,Pre,status-preparation\n200,In_action,Act,status-inprogress\n300,Review,Rev,status-review\n900,Completion,Comp,status-closed\n910,Pending,Pend,status-rejected"
        }
    ],
    "Aggregations": [
        {
            "Id": 1,
            "GroupBy": "Status",
            "Type": 0,
            "Target": ""
        },
        {
            "Id": 2,
            "GroupBy": "Owner",
            "Type": 0,
            "Target": ""
        },
        {
            "Id": 3,
            "GroupBy": "ClassA",
            "Type": 0,
            "Target": ""
        }
    ],
    "ViewLatestId": 0,
    "EnableBurnDown": false,
    "TitleSeparator": ")"
}