{
    "Id": "May",
    "Type": 110,
    "Languages": [
        {
            "Body": "May"
        },
        {
            "Language": "ja",
            "Body": "5月"
        },
        {
            "Language": "zh",
            "Body": "5月"
        },
        {
            "Language": "ko",
            "Body": "5월"
        },
        {
            "Language": "vi",
            "Body": "Có thể"
        },
        {
            "Language": "es",
            "Body": "Puede"
        },
        {
            "Language": "de",
            "Body": "Mai"
        }
    ]
}
