{
    "Id": "OutgoingMails_Cc",
    "ModelName": "OutgoingMail",
    "TableName": "OutgoingMails",
    "Label": "メール送信",
    "ColumnName": "Cc",
    "LabelText": "Cc",
    "No": "105",
    "History": "105",
    "EditorColumn": "105",
    "EditorEnabled": "1",
    "LinkColumn": "105",
    "HistoryColumn": "105",
    "TypeName": "nvarchar",
    "MaxLength": "-1",
    "Nullable": "1",
    "ByForm": "Forms.List(controlId).Join(\";\")",
    "LabelText_en": "Cc",
    "LabelText_zh": "抄送",
    "LabelText_de": "Cc",
    "LabelText_ko": "참조",
    "LabelText_es": "Cc",
    "LabelText_vn": "Cc"
}