{
    "Id": "Parameters_ParameterId",
    "ModelName": "Parameter",
    "TableName": "Parameters",
    "Label": "パラメータ",
    "ColumnName": "ParameterId",
    "LabelText": "パラメータID",
    "No": "1",
    "History": "1",
    "TypeName": "int",
    "Pk": "1",
    "PkHistory": "1",
    "Ix1": "2",
    "Identity": "1",
    "Seed": "1",
    "Required": "1",
    "NotForm": "1",
    "GenericUi": "1",
    "LabelText_en": "Parameter ID",
    "LabelText_zh": "参数ID",
    "LabelText_de": "Parameter-ID",
    "LabelText_ko": "매개변수 ID",
    "LabelText_es": "ID de parámetro",
    "LabelText_vn": "ID tham số"
}