{
    "Id": "Results_Locked",
    "ModelName": "Result",
    "TableName": "Results",
    "Label": "記録テーブル",
    "ColumnName": "Locked",
    "LabelText": "ロック",
    "No": "104",
    "History": "104",
    "Export": "104",
    "GridColumn": "104",
    "FilterColumn": "104",
    "FilterEnabled": "1",
    "EditorColumn": "104",
    "TitleColumn": "104",
    "LinkColumn": "104",
    "HistoryColumn": "104",
    "TypeName": "bit",
    "Ix3": "2",
    "Nullable": "1",
    "CopyByDefault": "1",
    "SettingEnable": "1",
    "LabelText_en": "Locked",
    "LabelText_zh": "已锁定",
    "LabelText_de": "Gesperrt",
    "LabelText_ko": "잠김",
    "LabelText_es": "Bloqueado",
    "LabelText_vn": "Khóa"
}