{
    "Id": "Sites_LockedTime",
    "ModelName": "Site",
    "TableName": "Sites",
    "Label": "サイト",
    "ColumnName": "LockedTime",
    "LabelText": "ロックした日時",
    "No": "119",
    "History": "119",
    "LinkColumn": "119",
    "HistoryColumn": "119",
    "TypeName": "datetime",
    "TypeCs": "Time",
    "RecordingData": ".Value",
    "Nullable": "1",
    "CreateAccessControl": "ManageService",
    "UpdateAccessControl": "ManageService",
    "NotForm": "1",
    "ByDataRow": "new Time(context, dataRow, column.ColumnName)",
    "NotEditorSettings": "1",
    "GridFormat": "Ymdahm",
    "EditorFormat": "Ymdahms",
    "ExportFormat": "Ymdahms",
    "LabelText_en": "Locked time",
    "LabelText_zh": "锁定时间",
    "LabelText_de": "Gesperrte Zeit",
    "LabelText_ko": "잠긴 시간",
    "LabelText_es": "Tiempo bloqueado",
    "LabelText_vn": "Thời gian khóa"
}